AdDownloader/__init__.py
AdDownloader/__main__.py
AdDownloader/adlib_api.py
AdDownloader/analysis.py
AdDownloader/app.py
AdDownloader/cli.py
AdDownloader/helpers.py
AdDownloader/media_download.py
AdDownloader/start_app.py
addownloader-0.2.12.dist-info/licenses/LICENSE.txt
addownloader-0.2.12.dist-info/METADATA
addownloader-0.2.12.dist-info/WHEEL
addownloader-0.2.12.dist-info/entry_points.txt
addownloader-0.2.12.dist-info/top_level.txt
addownloader-0.2.12.dist-info/RECORD
