Metadata-Version: 2.4
Name: AdDownloader
Version: 0.2.12
Summary: A cmd tool for downloading ads and their media content from the Meta Ad Library.
Author-email: Paula-Alexandra Gitu <paula.gitu@maastrichtuniversity.nl>
Maintainer-email: Paula-Alexandra Gitu <paula.gitu@maastrichtuniversity.nl>
License-Expression: GPL-3.0-or-later
Project-URL: Homepage, https://github.com/Paularossi/AdDownloader
Project-URL: Issues, https://github.com/Paularossi/AdDownloader/issues
Keywords: CLI tool,MetaAPI,AdLibrary,image scraping
Classifier: Development Status :: 3 - Alpha
Classifier: Programming Language :: Python
Classifier: Programming Language :: Python :: 3.9
Classifier: Programming Language :: Python :: 3.10
Classifier: Programming Language :: Python :: 3.11
Classifier: Operating System :: Microsoft :: Windows
Classifier: Operating System :: MacOS
Classifier: Intended Audience :: Developers
Classifier: Intended Audience :: Science/Research
Classifier: Topic :: Software Development :: Libraries :: Python Modules
Classifier: Topic :: Internet :: WWW/HTTP :: Indexing/Search
Requires-Python: >=3.9
License-File: LICENSE.txt
Requires-Dist: click==8.1.3
Requires-Dist: dash==2.15.0
Requires-Dist: datetime==5.4
Requires-Dist: gensim==4.3.2
Requires-Dist: inquirer3==0.4.0
Requires-Dist: meson==1.3.1
Requires-Dist: ninja==1.11.1.1
Requires-Dist: nltk==3.8.1
Requires-Dist: numpy==1.26.4
Requires-Dist: opencv-python==4.9.0.80
Requires-Dist: openpyxl==3.1.2
Requires-Dist: pandas==2.0.3
Requires-Dist: pillow==11.0.0
Requires-Dist: pytest>=6.2.4
Requires-Dist: requests==2.31.0
Requires-Dist: rich==13.6.0
Requires-Dist: scikit-image==0.22.0
Requires-Dist: scikit-learn==1.4.1.post1
Requires-Dist: scipy==1.12
Requires-Dist: selenium==4.16.0
Requires-Dist: setuptools>=43.0.0
Requires-Dist: textblob==0.17.1
Requires-Dist: torch==2.8.0
Requires-Dist: transformers>=4.37.2
Requires-Dist: typer==0.9.0
Requires-Dist: webdriver-manager==4.0.2
Dynamic: license-file
